diffnn/__init__.py
diffnn/__main__.py
diffnn/__version__.py
diffnn/cli.py
diffnn/logging.py
diffnn/utils.py
diffnn/nn/__init__.py
diffnn/nn/errors.py
diffnn/nn/onnx/__init__.py
diffnn/nn/onnx/utils.py
diffnn/nn/onnx/pytorch/__init__.py
diffnn/nn/onnx/pytorch/base.py
diffnn/nn/onnx/pytorch/operations.py
diffnn-0.0.1a0.dist-info/entry_points.txt
diffnn-0.0.1a0.dist-info/WHEEL
diffnn-0.0.1a0.dist-info/METADATA
diffnn-0.0.1a0.dist-info/RECORD
