Metadata-Version: 2.1
Name: diffnn
Version: 0.0.1a0
Summary: diffnn - differencing deep neural networks
Home-page: UNKNOWN
License: UNKNOWN
Author: David Shriver
Author-email: dls2fc@virginia.edu
Requires-Python: >=3.6
Requires-Dist: numpy==1.18
Requires-Dist: onnx==1.6
Requires-Dist: torch==1.3
Requires-Dist: torchvision==0.4
Requires-Dist: black ; extra == "dev"
Requires-Dist: flit ; extra == "dev"
Requires-Dist: sphinx ; extra == "doc"
Provides-Extra: dev
Provides-Extra: doc
